{
  "Merkez": ["Bahçelievler", "Cumhuriyet", "Atatürk", "Kurtuluş", "Yenimahalle", "Fatih", "İnönü", "Karşıyaka", "Şehitlik", "Yıldıztepe"],
  "Refahiye": ["Merkez", "Cumhuriyet", "Atatürk", "Kurtuluş", "Yenimahalle"],
  "İliç": ["Merkez", "Cumhuriyet", "Atatürk", "Kurtuluş", "Yenimahalle"],
  "Tercan": ["Merkez", "Cumhuriyet", "Atatürk", "Kurtuluş", "Yenimahalle"],
  "Kemah": ["Merkez", "Cumhuriyet", "Atatürk", "Kurtuluş", "Yenimahalle"],
  "Kemaliye": ["Merkez", "Cumhuriyet", "Atatürk", "Kurtuluş", "Yenimahalle"],
  "Otlukbeli": ["Merkez", "Cumhuriyet", "Atatürk", "Kurtuluş", "Yenimahalle"],
  "Üzümlü": ["Merkez", "Cumhuriyet", "Atatürk", "Kurtuluş", "Yenimahalle"],
  "Çayırlı": ["Merkez", "Cumhuriyet", "Atatürk", "Kurtuluş", "Yenimahalle"]
}
