{
  "Merkez": ["Bahçelievler", "Cumhuriyet", "Atatürk", "Kurtuluş", "Yenimahalle", "Fatih", "Çarşı", "Karşıyaka", "Yıldıztepe"],
  "Malazgirt": ["Merkez", "Cumhuriyet", "Atatürk", "Kurtuluş", "Yenimahalle"],
  "Bulanık": ["Merkez", "Cumhuriyet", "Atatürk", "Kurtuluş", "Yenimahalle"],
  "Varto": ["Merkez", "Cumhuriyet", "Atatürk", "Kurtuluş", "Yenimahalle"],
  "Hasköy": ["Merkez", "Cumhuriyet", "Atatürk", "Kurtuluş", "Yenimahalle"],
  "Korkut": ["Merkez", "Cumhuriyet", "Atatürk", "Kurtuluş", "Yenimahalle"]
}
